lndb_rest/__init__.py
lndb_rest/_check_versions.py
lndb_rest/main.py
lndb_rest/routers/__init__.py
lndb_rest/routers/introspection.py
lndb_rest/routers/metadata.py
lndb_rest/routers/wetlab.py
lndb_rest-0.4.0.dist-info/WHEEL
lndb_rest-0.4.0.dist-info/METADATA
lndb_rest-0.4.0.dist-info/RECORD
