Metadata-Version: 2.1
Name: lndb_rest
Version: 0.4.0
Summary: Rest API for a specific instance.
Author-email: Lamin Labs <laminlabs@gmail.com>
Requires-Dist: nbproject
Requires-Dist: fastapi[uvicorn]
Requires-Dist: uvicorn[standard]
Requires-Dist: lamindb==0.22.2
Requires-Dist: python-multipart
Requires-Dist: pre-commit ; extra == "dev"
Requires-Dist: nox ; extra == "dev"
Requires-Dist: pytest>=6.0 ; extra == "test"
Requires-Dist: pytest-cov ; extra == "test"
Project-URL: Home, https://github.com/laminlabs/lndb-rest
Provides-Extra: dev
Provides-Extra: test
